{
  "metadata": {
    "generatedAt": "2025-08-09T17:02:42.482Z",
    "projectRoot": "/mnt/d/dev/_ws/dep-graph-visualizer/example/example-app/src",
    "appDirectory": "/mnt/d/dev/_ws/dep-graph-visualizer/example/example-app/src/apps",
    "libsDirectory": "/mnt/d/dev/_ws/dep-graph-visualizer/example/example-app/src/libs",
    "stats": {
      "totalFiles": 11,
      "codeFiles": 8,
      "testFiles": 3,
      "totalCodeLines": 219,
      "totalTestLines": 65
    }
  },
  "graph": {
    "apps/dashboard/index.ts": {
      "imports": [
        "libs/api.ts",
        "libs/utils.ts",
        "libs/logger.ts"
      ],
      "importedBy": [
        "apps/main.ts"
      ],
      "linesOfCode": 43,
      "isTest": false,
      "importDetails": [
        {
          "path": "libs/api.ts",
          "symbols": [
            {
              "name": "api",
              "isTypeOnly": false
            }
          ],
          "isTypeOnly": false
        },
        {
          "path": "libs/utils.ts",
          "symbols": [
            {
              "name": "formatNumber",
              "isTypeOnly": false
            }
          ],
          "isTypeOnly": false
        },
        {
          "path": "libs/logger.ts",
          "symbols": [
            {
              "name": "Logger",
              "isTypeOnly": false
            }
          ],
          "isTypeOnly": false
        }
      ]
    },
    "apps/main.ts": {
      "imports": [
        "apps/style.css",
        "typescript.svg",
        "libs/counter.ts",
        "apps/dashboard/index.ts",
        "apps/user-profile/profile.ts"
      ],
      "importedBy": [],
      "linesOfCode": 27,
      "isTest": false,
      "importDetails": [
        {
          "path": "apps/style.css",
          "symbols": [],
          "isTypeOnly": false
        },
        {
          "path": "typescript.svg",
          "symbols": [
            {
              "name": "default",
              "alias": "typescriptLogo",
              "isTypeOnly": false
            }
          ],
          "isTypeOnly": false
        },
        {
          "path": "libs/counter.ts",
          "symbols": [
            {
              "name": "setupCounter",
              "isTypeOnly": false
            }
          ],
          "isTypeOnly": false
        },
        {
          "path": "apps/dashboard/index.ts",
          "symbols": [
            {
              "name": "default",
              "alias": "dashboard",
              "isTypeOnly": false
            }
          ],
          "isTypeOnly": false
        },
        {
          "path": "apps/user-profile/profile.ts",
          "symbols": [
            {
              "name": "createProfile",
              "isTypeOnly": false
            }
          ],
          "isTypeOnly": false
        }
      ]
    },
    "apps/user-profile/profile.ts": {
      "imports": [
        "libs/api.ts",
        "libs/validators.ts",
        "libs/logger.ts"
      ],
      "importedBy": [
        "apps/main.ts"
      ],
      "linesOfCode": 54,
      "isTest": false,
      "importDetails": [
        {
          "path": "libs/api.ts",
          "symbols": [
            {
              "name": "api",
              "isTypeOnly": false
            }
          ],
          "isTypeOnly": false
        },
        {
          "path": "libs/validators.ts",
          "symbols": [
            {
              "name": "isEmail",
              "isTypeOnly": false
            },
            {
              "name": "sanitizeInput",
              "isTypeOnly": false
            }
          ],
          "isTypeOnly": false
        },
        {
          "path": "libs/logger.ts",
          "symbols": [
            {
              "name": "Logger",
              "isTypeOnly": false
            }
          ],
          "isTypeOnly": false
        }
      ]
    },
    "libs/api.ts": {
      "imports": [
        "libs/logger.ts"
      ],
      "importedBy": [
        "apps/dashboard/index.ts",
        "apps/user-profile/profile.ts"
      ],
      "linesOfCode": 28,
      "isTest": false,
      "importDetails": [
        {
          "path": "libs/logger.ts",
          "symbols": [
            {
              "name": "defaultLogger",
              "isTypeOnly": false
            }
          ],
          "isTypeOnly": false
        }
      ]
    },
    "libs/counter.ts": {
      "imports": [
        "libs/utils.ts",
        "libs/logger.ts"
      ],
      "importedBy": [
        "apps/main.ts"
      ],
      "linesOfCode": 14,
      "isTest": false,
      "importDetails": [
        {
          "path": "libs/utils.ts",
          "symbols": [
            {
              "name": "formatNumber",
              "isTypeOnly": false
            }
          ],
          "isTypeOnly": false
        },
        {
          "path": "libs/logger.ts",
          "symbols": [
            {
              "name": "defaultLogger",
              "isTypeOnly": false
            }
          ],
          "isTypeOnly": false
        }
      ]
    },
    "libs/logger.ts": {
      "imports": [],
      "importedBy": [
        "apps/dashboard/index.ts",
        "apps/user-profile/profile.ts",
        "libs/api.ts",
        "libs/counter.ts"
      ],
      "linesOfCode": 23,
      "isTest": false,
      "importDetails": []
    },
    "libs/utils.ts": {
      "imports": [],
      "importedBy": [
        "apps/dashboard/index.ts",
        "libs/counter.ts",
        "libs/validators.ts"
      ],
      "linesOfCode": 13,
      "isTest": false,
      "importDetails": []
    },
    "libs/validators.ts": {
      "imports": [
        "libs/utils.ts"
      ],
      "importedBy": [
        "apps/user-profile/profile.ts"
      ],
      "linesOfCode": 17,
      "isTest": false,
      "importDetails": [
        {
          "path": "libs/utils.ts",
          "symbols": [
            {
              "name": "clamp",
              "isTypeOnly": false
            }
          ],
          "isTypeOnly": false
        }
      ]
    }
  }
}